teerss/__init__.py
teerss/main.py
teerss-0.1.1.dist-info/licenses/LICENSE
teerss-0.1.1.dist-info/METADATA
teerss-0.1.1.dist-info/WHEEL
teerss-0.1.1.dist-info/entry_points.txt
teerss-0.1.1.dist-info/top_level.txt
teerss-0.1.1.dist-info/RECORD
